stable_diffusion_videos/__init__.py
stable_diffusion_videos/app.py
stable_diffusion_videos/flax_stable_diffusion_pipeline.py
stable_diffusion_videos/image_generation.py
stable_diffusion_videos/stable_diffusion_pipeline.py
stable_diffusion_videos/upsampling.py
stable_diffusion_videos/utils.py
Jems_Video-0.8.1.dist-info/LICENSE
Jems_Video-0.8.1.dist-info/METADATA
Jems_Video-0.8.1.dist-info/WHEEL
Jems_Video-0.8.1.dist-info/top_level.txt
Jems_Video-0.8.1.dist-info/RECORD
