Metadata-Version: 2.1
Name: Jems-Video
Version: 0.8.1
Summary: Create 🔥 videos with Stable Diffusion by exploring the latent space and morphing between text prompts.
Home-page: UNKNOWN
Author: Jem
Author-email: 
License: Apache
Platform: UNKNOWN
Requires-Dist: av (<10.0.0)
Requires-Dist: diffusers (==0.19.3)
Requires-Dist: fire
Requires-Dist: fsspec (>=2023.4.0)
Requires-Dist: gradio
Requires-Dist: librosa
Requires-Dist: protobuf (==3.20.*)
Requires-Dist: realesrgan (==0.2.5.0)
Requires-Dist: scipy
Requires-Dist: transformers (>=4.21.0)
